iotapy/__init__.py
iotapy/iota.py
iotapy/iri.py
iotapy/storage/__init__.py
iotapy/storage/converter.py
iotapy/storage/tangle.py
iotapy/storage/providers/__init__.py
iotapy/storage/providers/rocksdb.py
iotapy/storage/providers/zmq.py
iotapy/storage/providers/types/__init__.py
iotapy/storage/providers/types/address.py
iotapy/storage/providers/types/approvee.py
iotapy/storage/providers/types/bundle.py
iotapy/storage/providers/types/milestone.py
iotapy/storage/providers/types/state_diff.py
iotapy/storage/providers/types/tag.py
iotapy/storage/providers/types/transaction.py
iotapy/storage/providers/types/transaction_metadata.py
iotapy-0.1.2.dist-info/LICENSE
iotapy-0.1.2.dist-info/WHEEL
iotapy-0.1.2.dist-info/METADATA
iotapy-0.1.2.dist-info/RECORD
