Metadata-Version: 1.2
Name: iotapy
Version: 0.1.2
Summary: A Pure-Python implementation of IOTA node
Home-page: https://github.com/mlouielu/iota-python
License: UNKNOWN
Author: Louie Lu
Author-email: git@louie.lu
Maintainer: Louie Lu
Maintainer-email: git@louie.lu
Requires-Python: >= 3
Classifier: License :: OSI Approved :: MIT License
Classifier: Programming Language :: Python :: 3
Classifier: Topic :: Software Development :: Libraries :: Python Modules
Classifier: Intended Audience :: Developers
Requires-Dist: pyota (>= 2.0.1)
Requires-Dist: python-rocksdb-iota (>= 0.7.2)
